terminal_chatapp/__main__.py
terminal_chatapp/cli.py
terminal_chatapp/client.py
terminal_chatapp/event.py
terminal_chatapp/input.py
terminal_chatapp/security.py
terminal_chatapp/server.py
terminal_chatapp-1.0.2.dist-info/LICENSE.txt
terminal_chatapp-1.0.2.dist-info/METADATA
terminal_chatapp-1.0.2.dist-info/WHEEL
terminal_chatapp-1.0.2.dist-info/top_level.txt
terminal_chatapp-1.0.2.dist-info/RECORD
