Metadata-Version: 2.1
Name: terminal-chatapp
Version: 1.0.2
Summary: Secure communication on terminal.
Home-page: https://github.com/clediscover/terminal_chatapp
Author: Mark Carcillar
License: UNKNOWN
Platform: UNKNOWN
Requires-Python: >=3.6
Requires-Dist: cryptography
Requires-Dist: websockets
